{
	"schemaVersion": 1,
	"id": "srcmov",
	"version": "${version}",
	
	"name": "Source Movement",
	"description": "This is an example description! Tell everyone what your mod is about!",
	"authors": [
		"Jorbonism"
	],
	"contact": {
		"homepage": "https://fabricmc.net/",
		"sources": ""
	},
	
	"license": "CC0-1.0",
	"icon": "assets/srcmov/icon.png",
	
	"environment": "*",
	"entrypoints": {
		"client": [
			"edu.jorbonism.source_movement.Srcmov"
		],
		"server": [
			"edu.jorbonism.source_movement.Srcmov"
		]
	},
	"mixins": [
		"srcmov.mixins.json"
	],
	
	"depends": {
		"fabricloader": ">=0.11.6",
		"fabric": "*",
		"minecraft": ">=1.17",
		"java": ">=16"
	}
}
